cijoe/linux/__init__.py
cijoe/linux/kmemleak.py
cijoe/linux/null_blk.py
cijoe/linux/configs/__init__.py
cijoe/linux/configs/default-config.toml
cijoe/linux/scripts/__init__.py
cijoe/linux/scripts/build_kdebs.py
cijoe/linux/scripts/null_blk.py
cijoe/linux/scripts/sysinfo.py
cijoe/linux/scripts/transfer_and_install_kdebs.py
cijoe/linux/selftest/__init__.py
cijoe/linux/selftest/test_kmemleak.py
cijoe/linux/selftest/test_null_blk.py
cijoe/linux/workflows/__init__.py
cijoe/linux/workflows/example-null_blk.yaml
cijoe/linux/workflows/example-workflow.yaml
cijoe_pkg_linux-0.9.10.dist-info/LICENSE
cijoe_pkg_linux-0.9.10.dist-info/METADATA
cijoe_pkg_linux-0.9.10.dist-info/WHEEL
cijoe_pkg_linux-0.9.10.dist-info/top_level.txt
cijoe_pkg_linux-0.9.10.dist-info/RECORD
